ltz_fourier_fitting/__init__.py
ltz_fourier_fitting/ltz_fourier_fittings.py
ltz_fourier_fitting-2.1.dist-info/METADATA
ltz_fourier_fitting-2.1.dist-info/WHEEL
ltz_fourier_fitting-2.1.dist-info/license.txt
ltz_fourier_fitting-2.1.dist-info/top_level.txt
ltz_fourier_fitting-2.1.dist-info/RECORD
